README.md
license.txt
setup.py
aimedic_utils_package.egg-info/PKG-INFO
aimedic_utils_package.egg-info/SOURCES.txt
aimedic_utils_package.egg-info/dependency_links.txt
aimedic_utils_package.egg-info/requires.txt
aimedic_utils_package.egg-info/top_level.txt
src/__init__.py
src/base/__init__.py
src/base/evaluation_interface.py
src/base/model_interface.py
src/evaluation_metrics/__init__.py
src/evaluation_metrics/classification/__init__.py
src/evaluation_metrics/classification/confidence_distribution.py
src/evaluation_metrics/classification/confusion_matrix.py
src/evaluation_metrics/classification/npv_specificity_curve.py
src/evaluation_metrics/classification/precision_recall.py
src/evaluation_metrics/classification/reliability_diagram.py
src/evaluation_metrics/classification/roc_curve.py
src/evaluation_metrics/classification/specificity_sensitivity_curve.py
src/models/__init__.py
src/models/aimedic_model.py
src/utils/__init__.py
src/utils/create_confusion_mat.py
src/utils/make_binary_pred.py
src/utils/model_utils.py
src/utils/set_mlflow_run.py